pydmo/__init__.py
pydmo/core.py
pydmo/utils.py
pydmo-0.0.1.dist-info/entry_points.txt
pydmo-0.0.1.dist-info/LICENSE
pydmo-0.0.1.dist-info/WHEEL
pydmo-0.0.1.dist-info/METADATA
pydmo-0.0.1.dist-info/RECORD
