Metadata-Version: 2.1
Name: pydmo
Version: 0.0.1
Summary: Pydmo: Build a database pydantic schema from its collection of data tables
Home-page: https://gitlab.com/strayMat/pydmo
License: EUPL-v1.2
Keywords: pydantic,data schema
Author: Matthieu Doutreligne
Author-email: matt.dout@gmail.com
Requires-Python: >=3.7.1,<4.0.0
Classifier: Intended Audience :: Developers
Classifier: License :: Other/Proprietary License
Classifier: Natural Language :: English
Classifier: Operating System :: OS Independent
Classifier: Programming Language :: Python
Classifier: Programming Language :: Python :: 3
Classifier: Programming Language :: Python :: 3.8
Classifier: Programming Language :: Python :: 3.9
Classifier: Programming Language :: Python :: Implementation :: CPython
Classifier: Topic :: Software Development :: Libraries :: Python Modules
Provides-Extra: docs
Requires-Dist: click (>=8.0.4,<9.0.0)
Requires-Dist: datamodel-code-generator (>=0.13.1,<0.14.0)
Requires-Dist: importlib-metadata (>=4.11.3,<5.0.0); extra == "docs"
Requires-Dist: jinja2 (<3.1); extra == "docs"
Requires-Dist: jupyter (>=1.0.0,<2.0.0)
Requires-Dist: jupytext (>=1.13.7,<2.0.0)
Requires-Dist: myst-parser (>=0.17.0,<0.18.0); extra == "docs"
Requires-Dist: pandas (>=1.3.0,<2.0.0)
Requires-Dist: pre-commit (>=2.20.0,<3.0.0)
Requires-Dist: pydata-sphinx-theme (>=0.8.0,<0.9.0); extra == "docs"
Requires-Dist: pygments (>=2.11.2,<3.0.0); extra == "docs"
Requires-Dist: python-dotenv (>=0.20.0,<0.21.0)
Requires-Dist: sphinx (>=4.4.0,<5.0.0); extra == "docs"
Requires-Dist: sphinx-autodoc-typehints (>=1.17.0,<2.0.0); extra == "docs"
Requires-Dist: sphinx-click (>=3.1.0,<4.0.0); extra == "docs"
Requires-Dist: sphinxcontrib-apidoc (>=0.3.0,<0.4.0); extra == "docs"
Project-URL: Repository, https://gitlab.com/strayMat/pydmo
